{
    "methodCalls": [
        {
            "class": "\\EntityWranglerTest\\Hydrator\\HydratorRegistry",
            "method": "hydrate",
            "position": 0
        },
        {
            "class": "\\Auryn\\Injector",
            "method": "make",
            "position": 0
        }
    ],
    "functionCalls": [
        {
            "function": "\\mock",
            "position": 0
        },
        {
            "function": "\\mockObjects",
            "position": 0
        }
        
    ]
}

